LICENSE
tablecv/__init__.py
tablecv/extract_table.py
tablecv/tests/__init__.py
tablecv/tests/test_basic.py
tablecv/utils/__init__.py
tablecv/utils/bounding_box.py
tablecv/utils/table_extraction.py
tablecv-0.1.1.dist-info/LICENSE
tablecv-0.1.1.dist-info/METADATA
tablecv-0.1.1.dist-info/WHEEL
tablecv-0.1.1.dist-info/RECORD
