Metadata-Version: 2.1
Name: tablecv
Version: 0.1.1
Summary: Table extraction from image.
Home-page: https://github.com/inquilabee/TableCV
License: MIT
Keywords: opencv,opencv python,python table image,python table extraction
Author: Vishal Kumar Mishra
Author-email: vishal.k.mishra2@gmail.com
Requires-Python: >=3.10,<4.0
Classifier: License :: OSI Approved :: MIT License
Classifier: Programming Language :: Python :: 3
Classifier: Programming Language :: Python :: 3.10
Classifier: Programming Language :: Python :: 3.11
Requires-Dist: django-environ (>=0.11.2,<0.12.0)
Requires-Dist: opencv-contrib-python (==4.5.4.60)
Requires-Dist: opencv-python (==4.5.4.60)
Requires-Dist: opencv-python-headless (==4.5.4.60)
Requires-Dist: paddleocr (==2.7.0.2)
Requires-Dist: paddlepaddle (==2.4.2)
Requires-Dist: pandas (>=2.1.0,<3.0.0)
Requires-Dist: pytesseract (>=0.3.10,<0.4.0)
Requires-Dist: python-dotenv (>=1.0.0,<2.0.0)
Requires-Dist: pyyaml (>=6.0.1,<7.0.0)
Requires-Dist: shapely (>=2.0.1,<3.0.0)
Project-URL: Repository, https://github.com/inquilabee/TableCV
